tags_input/__about__.py
tags_input/__init__.py
tags_input/admin.py
tags_input/exceptions.py
tags_input/fields.py
tags_input/urls.py
tags_input/utils.py
tags_input/views.py
tags_input/widgets.py
tags_input/static/jquery-3.2.1.min.js
tags_input/static/jquery-ui-1.12.1.min.css
tags_input/static/jquery-ui-1.12.1.min.js
tags_input/static/jquery.tagsinput-revisited-2.0.min.css
tags_input/static/jquery.tagsinput-revisited-2.0.min.js
tags_input/templates/tags_input_widget.html
django_tags_input-6.0.0.dist-info/METADATA
django_tags_input-6.0.0.dist-info/WHEEL
django_tags_input-6.0.0.dist-info/top_level.txt
django_tags_input-6.0.0.dist-info/RECORD
