Metadata-Version: 2.1
Name: django-tags-input
Version: 6.0.0
Summary: Django jQuery Tags Input is a Django field and widget wrapper that adds an easy to use interface for `ManyToManyField` and `ForeignKey` fields in the forms of autocompleting tags with optionally live creation of new linked items
Home-page: https://github.com/WoLpH/django-tags-input
Author: Rick van Hattem
Author-email: wolph@wol.ph
License: BSD
Classifier: Development Status :: 5 - Production/Stable
Classifier: Environment :: Web Environment
Classifier: Intended Audience :: Developers
Classifier: License :: OSI Approved :: BSD License
Classifier: Natural Language :: English
Classifier: Programming Language :: Python :: 3.7
Classifier: Programming Language :: Python :: 3.8
Classifier: Programming Language :: Python :: 3.9
Classifier: Programming Language :: Python :: 3.10
Classifier: Programming Language :: Python :: 3.11
Provides-Extra: docs
Provides-Extra: tests
